consolejs/Console.py
consolejs/__init__.py
consolejs/disabled.py
consolejs/expr_debug.py
consolejs/formats.py
consolejs/impl.py
tests/__init__.py
tests/test_dir.py
tests/test_disabled.py
tests/test_selfmodule.py
tests/pkg1/EnvVar.py
tests/pkg1/TimeTools.py
tests/pkg1/__init__.py
consolejs-1.0.9.dist-info/LICENSE-MIT
consolejs-1.0.9.dist-info/METADATA
consolejs-1.0.9.dist-info/WHEEL
consolejs-1.0.9.dist-info/top_level.txt
consolejs-1.0.9.dist-info/RECORD
